core_extensions/__init__.py
core_extensions/py.typed
core_extensions/decorators/__init__.py
core_extensions/decorators/retry.py
core_extensions-1.0.0.dist-info/licenses/LICENSE
core_extensions-1.0.0.dist-info/METADATA
core_extensions-1.0.0.dist-info/WHEEL
core_extensions-1.0.0.dist-info/top_level.txt
core_extensions-1.0.0.dist-info/RECORD
